ping_me/engine.py
ping_me/authenticate.py
ping_me/release.py
ping_me/ping.py
ping_me/__init__.py
ping_me/GET.py
ping_me/depends/text2num.py
ping_me/depends/__init__.py
ping_me/data/module_locator.py
ping_me/data/countrylist.py
ping_me/data/__init__.py
ping_me/utils/cryptex.py
ping_me/utils/__init__.py
ping_me-0.3.dist-info/metadata.json
ping_me-0.3.dist-info/METADATA
ping_me-0.3.dist-info/WHEEL
ping_me-0.3.dist-info/RECORD
ping_me-0.3.dist-info/entry_points.txt
ping_me-0.3.dist-info/DESCRIPTION.rst
ping_me-0.3.dist-info/top_level.txt
