Metadata-Version: 2.0
Name: ping-me
Version: 0.3
Summary: Cross platform personalized ping
Home-page: https://github.com/OrkoHunter/ping-me
Author: Himanshu Mishra
Author-email: himanshumishra@iitkgp.ac.in
License: Apache License
Keywords: ping me reminder cross platform
Platform: UNKNOWN
Requires-Dist: phonenumbers
Requires-Dist: requests
Requires-Dist: pycrypto
Requires-Dist: python-dateutil
Requires-Dist: parsedatetime
